eitps-1.0.0b2.dist-info/licenses/LICENSE.txt
powerscript/__init__.py
powerscript/auto_compile.py
powerscript/cli/__init__.py
powerscript/cli/cli.py
powerscript/cli/commands.py
powerscript/cli/project_creator.py
powerscript/compiler/__init__.py
powerscript/compiler/advanced_ast.py
powerscript/compiler/ast_nodes.py
powerscript/compiler/extended_features.py
powerscript/compiler/lexer.py
powerscript/compiler/parser.py
powerscript/compiler/transpiler.py
powerscript/lsp/__init__.py
powerscript/lsp/handlers.py
powerscript/lsp/protocol.py
powerscript/lsp/server.py
powerscript/runtime/__init__.py
powerscript/runtime/access_modifiers.py
powerscript/runtime/async_helpers.py
powerscript/runtime/builtins.py
powerscript/runtime/database.py
powerscript/runtime/enums.py
powerscript/runtime/file_system.py
powerscript/runtime/gui.py
powerscript/runtime/networking.py
powerscript/runtime/runtime_validator.py
powerscript/typechecker/__init__.py
powerscript/typechecker/pyright_integration.py
powerscript/typechecker/static_analyzer.py
powerscript/typechecker/type_checker.py
powerscript/typechecker/type_inference.py
powerscript/vscode-extension/language-configuration.json
powerscript/vscode-extension/package.json
powerscript/vscode-extension/snippets/powerscript.json
powerscript/vscode-extension/src/extension.ts
powerscript/vscode-extension/syntaxes/powerscript.tmLanguage.json
eitps-1.0.0b2.dist-info/METADATA
eitps-1.0.0b2.dist-info/WHEEL
eitps-1.0.0b2.dist-info/entry_points.txt
eitps-1.0.0b2.dist-info/top_level.txt
eitps-1.0.0b2.dist-info/RECORD
