Metadata-Version: 2.4
Name: eitps
Version: 1.0.0b2
Summary: Typed PowerScript (TPS) - A fully structured development language that transpiles to Python
Home-page: https://github.com/SaleemLww/PowerScript-EITPS
Author: Saleem Ahmad (Elite India Org Team)
Author-email: Saleem Ahmad <team@eliteindia.org>
Maintainer-email: PowerScript Team <team@eliteindia.org>
License: MIT
Project-URL: Homepage, https://github.com/SaleemLww/PowerScript-EITPS
Project-URL: Repository, https://github.com/SaleemLww/PowerScript-EITPS
Project-URL: Documentation, https://github.com/SaleemLww/PowerScript-EITPS/blob/master/README.md
Project-URL: Bug Reports, https://github.com/SaleemLww/PowerScript-EITPS/issues
Project-URL: Changelog, https://github.com/SaleemLww/PowerScript-EITPS/releases
Keywords: tps,powerscript,typed,python,transpiler,compiler,language,ai
Classifier: Development Status :: 4 - Beta
Classifier: Intended Audience :: Developers
Classifier: License :: OSI Approved :: MIT License
Classifier: Programming Language :: Python :: 3
Classifier: Programming Language :: Python :: 3.8
Classifier: Programming Language :: Python :: 3.9
Classifier: Programming Language :: Python :: 3.10
Classifier: Programming Language :: Python :: 3.11
Classifier: Programming Language :: Python :: 3.12
Classifier: Topic :: Software Development :: Compilers
Classifier: Topic :: Software Development :: Code Generators
Classifier: Topic :: Software Development :: Libraries :: Python Modules
Requires-Python: >=3.8
License-File: LICENSE.txt
Requires-Dist: beartype>=0.10.0
Requires-Dist: lark>=1.1.0
Requires-Dist: watchdog>=2.1.0
Requires-Dist: rich>=10.0.0
Requires-Dist: click>=8.0.0
Requires-Dist: typing-extensions>=4.0.0
Provides-Extra: dev
Requires-Dist: pytest>=6.0.0; extra == "dev"
Requires-Dist: pytest-cov>=2.10.0; extra == "dev"
Requires-Dist: black>=21.0.0; extra == "dev"
Requires-Dist: flake8>=3.8.0; extra == "dev"
Requires-Dist: mypy>=0.910; extra == "dev"
Provides-Extra: lsp
Requires-Dist: pygls>=0.11.0; extra == "lsp"
Requires-Dist: pyright>=1.1.0; extra == "lsp"
Provides-Extra: ai
Requires-Dist: numpy>=1.21.0; extra == "ai"
Requires-Dist: pandas>=1.3.0; extra == "ai"
Requires-Dist: scikit-learn>=1.0.0; extra == "ai"
Requires-Dist: torch>=1.9.0; extra == "ai"
Provides-Extra: web
Requires-Dist: flask>=2.0.0; extra == "web"
Requires-Dist: fastapi>=0.70.0; extra == "web"
Requires-Dist: uvicorn>=0.15.0; extra == "web"
Dynamic: author
Dynamic: home-page
Dynamic: license-file
Dynamic: requires-python
